[{"id_message": 31650600534, "message": "Hola me llamo Vane . y yo llevo desde los 8a\u00f1os con depresiones ansiedad ... En 35 a\u00f1os nunca ped\u00ed ayuda , ni sab\u00eda el el cari\u00f1o es muy importante . Yo soy una persona , bipolar.eso me dicen.me afecta mucho las cosas , y llega el momento en que cuando las cosas no me salen bien ... caigo en un pozo . y solo quiero desaparecer o morir . Creo que estoy de paso", "date": "2021-05-23 12:15:01"}, {"id_message": 31650600534, "message": "Ya eso intento , pero siempre intente llevar las cosas sola y salir sola .", "date": "2021-05-23 12:51:05"}, {"id_message": 31650600534, "message": "Intento buscar soluciones , para estar bien sin falta de ir a m\u00e9dicos . yo creo que los mejores m\u00e9dicos somos nosotros.por que pasamos situaciones ... y podemos ayudarnos .", "date": "2021-05-23 12:52:44"}, {"id_message": 31650600534, "message": "Ya pero no quiero molestar , y como hasta ahora solo me ayudaron con pastillas . Yo suelo escribir para desahogar , pero luego sigo igual", "date": "2021-05-23 12:54:41"}, {"id_message": 31650600534, "message": "Hola Ana , en que est\u00e1s desacuerdo ?", "date": "2021-05-23 12:55:25"}, {"id_message": 31650600534, "message": "Nunca desconf\u00ede tanto de la gente", "date": "2021-05-23 12:55:37"}, {"id_message": 31650600534, "message": "Estoy con medicaci\u00f3n , pero no me ayuda.solo cuando me dan ataques de ansiedad", "date": "2021-05-23 12:56:07"}, {"id_message": 31650600534, "message": "Mi siquiatra me dice , que parece mentira que mis a\u00f1os este a si.que no somos ni\u00f1os de parbulario.por eso , paso . y mi sicilogo tampoco me ayudo", "date": "2021-05-23 12:59:37"}, {"id_message": 31650600534, "message": "Hay momentos que tengo impulsos que no puedo controlar , por que es que en segundos se me va la cabeza y me queda en 0 , y no m acuerdo de lo wu hago .", "date": "2021-05-23 13:01:02"}, {"id_message": 31650600534, "message": "Yo siempre ped\u00ed que por lo menos me dejasen para cuando me dan a rawu s de ansiedad , por que tengo miedo hacer da\u00f1o a los wu me rodean .", "date": "2021-05-23 13:01:58"}, {"id_message": 31650600534, "message": "Eso quer\u00eda hacer , me digeron de uno muy bueno , pero de pago , pero cuando est\u00e1s mal pagas lo que puedes , y que tal cambia la vida.pero yo digo para wu est\u00e1n los del ambulatorio ...", "date": "2021-05-23 13:03:29"}, {"id_message": 31650600534, "message": "Pues si en mede ayudarte te unden m\u00e1s . y al final pues pienso que todo lo que pasa al mi alrededor es por culpa m\u00eda .", "date": "2021-05-23 13:05:40"}, {"id_message": 31650600534, "message": "Me dejaron teanquimacin , y compresa.por que yo trabajo y la medicaci\u00f3n no me deja trabajar", "date": "2021-05-23 13:06:32"}, {"id_message": 31650600534, "message": "Mira os voy a contar la situaci\u00f3n de un conocido que lleva muchos a\u00f1os con tratamiento y el otro d\u00eda fue al ambulatorio con un cuchillo pero un cuchillo grande y ahora te digo una escopeta y entr\u00f3 amenazando y sali\u00f3 el de seguridad y lo que le dijo el de seguridad tranquil\u00edzate Javi y los del ambulatorio no hicieron nada le pincharon 7 veces y me dijeron que fuese por el Lucas a ingresar y le dijo que \u00e9l lo iba ni obligatorio y voluntario el caso es que le dejaron salir del ambulatorio o una persona con problemas psiqui\u00e1tricos graves no me parece normal ayudar as\u00ed a la gente", "date": "2021-05-23 13:15:31"}, {"id_message": 31650600534, "message": "Qu\u00e9 es una persona que alomejor controla porque yo lo vi y le dije Javi ingresa antes que \u00e9l y es tomates alguien y no quiso", "date": "2021-05-23 13:16:00"}, {"id_message": 31650600534, "message": "Entonces qu\u00e9 piensas que al final tienes que salir solo de todo", "date": "2021-05-23 13:16:15"}, {"id_message": 31650600534, "message": "Eso intento hacer . Buscar y hacer algo que me ayude a soltar todo que llevo dentro ... y poder estar bien , y tranquila de una vez", "date": "2021-05-23 20:08:45"}, {"id_message": 31650600534, "message": "Hola buenas tardes . Pues a m\u00ed nunca me pasaba.Pero ahora cuando estoy con la menstruaci\u00f3n , unos d\u00edas antes y lo que me dura , me altera .", "date": "2021-05-24 13:33:40"}]