[{"id_message": 31650600534, "message": "Es todo lo que necesito , gracias \ud83e\udd29", "date": "2021-02-21 09:48:17"}, {"id_message": 31650600534, "message": "Me pod\u00e9is decir un poco de qu\u00e9 va el grupo ?", "date": "2021-02-21 10:04:13"}, {"id_message": 31650600534, "message": "Bon dia ! Una pregunta , alguno se despierta ya acelerado por la ma\u00f1ana ? Qu\u00e9 hac\u00e9is para frenar la sensaci\u00f3n de que el coraz\u00f3n quiere ir por libre ?", "date": "2021-02-22 09:03:57"}, {"id_message": 31650600534, "message": "A m\u00ed me dijo la m\u00e9dica que si me mareaba era porque mi mente iba m\u00e1s r\u00e1pida que yo y no asimilaba bien lo que ve\u00eda , me emparanoiaba mucho . Ahora cuando tengo la sensaci\u00f3n : me paro a respirar un poco y baja", "date": "2021-02-22 12:59:01"}, {"id_message": 31650600534, "message": "Para la meditaci\u00f3n , usais alguna app ? O alg\u00fan canal espec\u00edfico de youtube ?", "date": "2021-02-22 13:10:45"}, {"id_message": 31650600534, "message": "Tomo nota , muchas gracias \ud83e\udd70", "date": "2021-02-22 13:14:05"}, {"id_message": 31650600534, "message": "Yo tampoco estoy tomando nada actualmente . Estuve con medicaci\u00f3n 6 meses , pero me la quitaron porque mejor\u00e9 . Cada persona es un mundo , ni estupido ni fuerte . Diferentes .", "date": "2021-02-22 17:14:50"}, {"id_message": 31650600534, "message": "Gracias por tus palabras , reconfortan mucho", "date": "2021-02-22 19:19:58"}, {"id_message": 31650600534, "message": "Yo tambi\u00e9n tengo una pregunta / consulta . Ayer tuve una crisis que me arrastr\u00f3 todo el d\u00eda , hoy me he levantado plof , no es igual que ayer pero estoy plof total , si os ha pasado , os pregunto : es consecuencia de ayer ( como secuelas ) ? Si os ha pasado , os ha durado mucho ? Qu\u00e9 frustrante es cuando llevas un tiempo bien \ud83d\ude22", "date": "2021-03-28 12:56:43"}, {"id_message": 31650600534, "message": "Yo cuando me da me pongo a hacer algo , no intento relajarme porque me centro en el coraz\u00f3n y tengo la sensaci\u00f3n de que se acelera m\u00e1s", "date": "2021-03-28 19:19:14"}, {"id_message": 31650600534, "message": "Tienes que saber si es una taquicardia real ( que se te acelera el pulso ) o infundada ( que te da esa sensaci\u00f3n ) , las m\u00edas muchas veces no son reales . Me tomo el pulso y lo tengo bien", "date": "2021-03-28 19:20:12"}, {"id_message": 31650600534, "message": "Por afirmaciones as\u00ed se ignoran estas patolog\u00edas", "date": "2021-04-02 16:07:55"}, {"id_message": 31650600534, "message": "No , no me ofende . No entiendo la necesidad de entrar en un grupo con gente que sufre a decir eso", "date": "2021-04-02 16:10:01"}, {"id_message": 31650600534, "message": "Prueba el m\u00e9todo jacobson de la relajaci\u00f3n progresiva muscular . A m\u00ed me lo recomendaron", "date": "2021-05-04 20:24:00"}]