[{"id_message": 31650600534, "message": "Opiniones de escitalopran en gotas ? Da sintomas ?", "date": "2021-04-30 10:55:26"}, {"id_message": 31650600534, "message": "Alguien que la ansiedad le haya dado febricula permanente ?", "date": "2021-04-30 10:55:54"}, {"id_message": 31650600534, "message": "Pero da sintomas o algo el escitalopran en gotas ?", "date": "2021-04-30 11:10:59"}, {"id_message": 31650600534, "message": "Pero depende de la cantidad q tomes no ? Yo son 3 gotas", "date": "2021-04-30 11:11:41"}, {"id_message": 31650600534, "message": "Llevo 3 a\u00f1os con ansiedad generalizada y agorafobia con psicologo y tal he mejorado bastante ... de hecho vivo en otra ciudad ahora . Pero desde hace unos meses me esta dando sintomas en la vista . Vision borrosa constantemente", "date": "2021-04-30 11:14:49"}, {"id_message": 31650600534, "message": "Pues estoy enferma desde los 9 a\u00f1os . Algo ha ayudao eso", "date": "2021-04-30 11:16:25"}, {"id_message": 31650600534, "message": "Mi enfermedad . A cualquier enfermo cronico le pasa", "date": "2021-04-30 11:17:50"}, {"id_message": 31650600534, "message": "Por mi enfermedad xD", "date": "2021-04-30 11:18:40"}, {"id_message": 31650600534, "message": "Que afecta sobre todo en colon", "date": "2021-04-30 11:19:42"}, {"id_message": 31650600534, "message": "Y lo q estas tomando no ? Xs", "date": "2021-04-30 11:27:53"}, {"id_message": 31650600534, "message": "Que va si he ido", "date": "2021-04-30 12:22:01"}, {"id_message": 31650600534, "message": "Y me hice hasta fondo de ojo", "date": "2021-04-30 12:22:07"}, {"id_message": 31650600534, "message": "No me acostumbro a la vision borrosa x esto ...", "date": "2021-04-30 13:04:46"}, {"id_message": 31650600534, "message": "Me da mareo xd", "date": "2021-04-30 13:04:51"}, {"id_message": 31650600534, "message": "La llevo bastante bien", "date": "2021-04-30 13:05:21"}, {"id_message": 31650600534, "message": "La vision borrosa dices ?", "date": "2021-04-30 13:06:33"}, {"id_message": 31650600534, "message": "Pero me dura dias", "date": "2021-04-30 13:06:37"}, {"id_message": 31650600534, "message": "Es super incomodo porque miro a todas las cosas de la casa o en la calle y demas .. y no enfoca", "date": "2021-04-30 13:07:25"}, {"id_message": 31650600534, "message": "Veias negro o que ?", "date": "2021-04-30 13:07:38"}, {"id_message": 31650600534, "message": "Pf es lo q peor llevo", "date": "2021-04-30 13:08:21"}, {"id_message": 31650600534, "message": "Bueno de todos los sintomas que he tenio .. El.peor es este", "date": "2021-04-30 13:10:44"}, {"id_message": 31650600534, "message": "Porque no ves bien en todo el dia", "date": "2021-04-30 13:10:58"}]