[{"id_message": 31650600534, "message": "Hola a todos llevo 3 a\u00f1os con ansiedad generalizada y no se cual es el desencadenante", "date": "2022-01-19 02:18:32"}, {"id_message": 31650600534, "message": "La verdad si y muy agotador porque a mi me produce insomnio", "date": "2022-01-19 02:33:23"}, {"id_message": 31650600534, "message": "Si frustraci\u00f3n creo yo y los m\u00e1s cercanos est\u00e1n frustrados por mi propia frustraci\u00f3n creo yo que es el caso de mis padres por el fracaso de mi matrimonio", "date": "2022-01-19 02:35:12"}, {"id_message": 31650600534, "message": "Yo voy a terapia y no siento que voy avanzando", "date": "2022-01-19 02:35:51"}, {"id_message": 31650600534, "message": "La verdad no se enfoca en ning\u00fan camino", "date": "2022-01-19 02:36:36"}, {"id_message": 31650600534, "message": "Yo habl\u00e9 con la psic\u00f3loga y le dije que quiero terapia cognitiva conductual pero se qued\u00f3 solo en palabras", "date": "2022-01-19 02:37:29"}, {"id_message": 31650600534, "message": "Si la verdad si me alegro mucho por mi familia no parece entender la dimensi\u00f3n del problema m\u00edo", "date": "2022-01-19 02:38:53"}, {"id_message": 31650600534, "message": "Si ya cambie de Psicologo 3 veces", "date": "2022-01-19 02:39:38"}, {"id_message": 31650600534, "message": "A mi la ansiedad me ataca por las noches me da taquicardias dolor abdominal alucinaciones a veces", "date": "2022-01-19 02:40:41"}, {"id_message": 31650600534, "message": "Yo igual que Ana", "date": "2022-01-19 02:43:32"}, {"id_message": 31650600534, "message": "De insomnio un 8 de ansiedad un 6 de espasmo y lo dem\u00e1s va ratos hay d\u00edas nulos y d\u00edas duros", "date": "2022-01-19 02:44:21"}, {"id_message": 31650600534, "message": "Yo tomo alprazolam y lorazepam", "date": "2022-01-19 02:46:45"}, {"id_message": 31650600534, "message": "Si dos ansioliticos y un hipn\u00f3tico", "date": "2022-01-19 02:47:33"}, {"id_message": 31650600534, "message": "Lorazepam si uno or ls ma\u00f1ana y otro por la noche", "date": "2022-01-19 02:49:00"}, {"id_message": 31650600534, "message": "Si llevo 2 a\u00f1os con l mediaci\u00f3n", "date": "2022-01-19 02:50:19"}]