[{"id_message": 31650600534, "message": "Hola , a alguien de vosotros os costaba tragar tambi\u00e9n ?", "date": "2021-09-14 03:33:35"}, {"id_message": 31650600534, "message": "Yo tengo la sensaci\u00f3n de que al tragar me ahogo con la comida o se queda ah\u00ed pillada o baja muy lento os a pasado ?", "date": "2021-09-14 03:34:14"}, {"id_message": 31650600534, "message": "Y tambi\u00e9n os a pasado que teneis como n\u00e1useas asi tipo de asco durante las 24 horas del dia ?", "date": "2021-09-14 03:45:36"}, {"id_message": 31650600534, "message": "El jueves me hacen una gastroscopia , como fue vuestra experiencia ?", "date": "2021-09-14 15:18:23"}, {"id_message": 31650600534, "message": "Esq tengo 19 a\u00f1os y estoy un poco cagado jajajaj", "date": "2021-09-14 15:18:50"}, {"id_message": 31650600534, "message": "Desde mayo empec\u00e9 con que ten\u00eda n\u00e1useas las 24 horas del dia , todos los dias y desde hace 1 mes y poco empec\u00e9 con problemas para tragar como si no pudiera tragar bien , es como si la comida para muy lento o se quedara ah\u00ed", "date": "2021-09-14 15:36:01"}, {"id_message": 31650600534, "message": "De q creeis a pueda ser , os a pasado ?", "date": "2021-09-14 15:50:07"}, {"id_message": 31650600534, "message": "Las pruebas de la gastroscopia te la dan el mismo dia ?", "date": "2021-09-14 16:03:24"}, {"id_message": 31650600534, "message": "Buenas , alguien de aqu\u00ed toma besitran ?", "date": "2021-09-15 16:57:16"}, {"id_message": 31650600534, "message": "Que te pasa en el est\u00f3mago ?", "date": "2021-09-15 18:09:11"}, {"id_message": 31650600534, "message": "Yo e empezao de repente que respiro y noto que no e llegado el pecho", "date": "2021-09-18 01:31:03"}, {"id_message": 31650600534, "message": "No me da esa tranquilidad de haber respirado bien", "date": "2021-09-18 01:31:15"}, {"id_message": 31650600534, "message": "Una sensaci\u00f3n muy rara", "date": "2021-09-18 01:31:22"}, {"id_message": 31650600534, "message": "A vosotros cuando haceis deporte no os cuesta mas cuando tenias mas ansiedad que cuando menos ?", "date": "2021-09-18 13:31:13"}]